geometricalgebra/__init__.py
geometricalgebra/algebra.py
geometricalgebra/cayley.py
geometricalgebra/cga.py
geometricalgebra/cga2d.py
geometricalgebra/cga3d.py
geometricalgebra/cga4d.py
geometricalgebra/coherent_point_drift.py
geometricalgebra/tests/test_algebra.py
geometricalgebra/tests/test_cayley.py
geometricalgebra/tests/test_coherent_point_drift.py
geometricalgebra/tests/test_gradient.py
geometricalgebra/tests/test_quaterion_interpolation.py
geometricalgebra/tests/test_tensorflow.py
geometricalgebra/tests/test_vector.py
geometricalgebra/tests/test_versor.py
geometricalgebra/utils.py
geometricalgebra/vector.py
geometricalgebra/viewer.py
geometricalgebra-0.1.3.dist-info/LICENSE
geometricalgebra-0.1.3.dist-info/METADATA
geometricalgebra-0.1.3.dist-info/WHEEL
geometricalgebra-0.1.3.dist-info/RECORD
