Metadata-Version: 2.1
Name: geometricalgebra
Version: 0.1.3
Summary: A package for conformal geometric algebra
Author: Daniel Vorberg
Author-email: daniel.vorberg@wandelbots.com
Requires-Python: >=3.9,<4.0
Classifier: Programming Language :: Python :: 3
Classifier: Programming Language :: Python :: 3.9
Classifier: Programming Language :: Python :: 3.10
Classifier: Programming Language :: Python :: 3.11
Classifier: Programming Language :: Python :: 3.12
Provides-Extra: all
Requires-Dist: jax (>=0.4.27) ; extra == "all"
Requires-Dist: jaxlib (>=0.4.27) ; extra == "all"
Requires-Dist: matplotlib (>=3.4.2) ; extra == "all"
Requires-Dist: numpy (>=1.19.0)
Requires-Dist: scipy (>=1.8.0)
Requires-Dist: tensorflow (>=2.16.1) ; extra == "all"
